Metadata-Version: 2.1
Name: jail
Version: 0.0.14
Summary: Native FreeBSD jail bindings with libc.
Home-page: https://github.com/gronke/py-jail
Author: Stefan Grönke
Author-email: stefan@gronke.net
License: UNKNOWN
Platform: UNKNOWN
Requires-Python: >=3.6
